sqlbind/__init__.py
sqlbind/py.typed
sqlbind-1.2.dist-info/LICENSE
sqlbind-1.2.dist-info/METADATA
sqlbind-1.2.dist-info/WHEEL
sqlbind-1.2.dist-info/top_level.txt
sqlbind-1.2.dist-info/RECORD
