Metadata-Version: 2.1
Name: sqlbind
Version: 1.2
Summary: sqlbind allows to bind parameters in text based raw SQL queries
Author: Anton Bobrov
Author-email: baverman+pypi@gmail.com
License: MIT
Classifier: Programming Language :: Python :: 3
Classifier: License :: OSI Approved :: MIT License
Classifier: Operating System :: OS Independent
Requires-Python: >=3.6
License-File: LICENSE
